sims/__init__.py
sims/lut.py
sims/sims.py
sims/transparent.py
sims/utils.py
sims/lut/IC20.lut
sims/lut/LN85.lut
sims/lut/PH16.lut
sims/lut/binary.lut
sims/lut/blue.lut
sims/lut/bw.lut
sims/lut/bw128.lut
sims/lut/bw64.lut
sims/lut/cameca.lut
sims/lut/cool.lut
sims/lut/falsecolor1.lut
sims/lut/falsecolor2.lut
sims/lut/falsecolor3.lut
sims/lut/falsecolor4.lut
sims/lut/green.lut
sims/lut/greyinverse.lut
sims/lut/limagecolors.tbl
sims/lut/pseudo.lut
sims/lut/rainbow.lut
sims/lut/rainbowinverse.lut
sims/lut/red.lut
sims/lut/temp.lut
sims/lut/warm.lut
sims-2.0.2.dist-info/LICENSE.md
sims-2.0.2.dist-info/METADATA
sims-2.0.2.dist-info/WHEEL
sims-2.0.2.dist-info/top_level.txt
sims-2.0.2.dist-info/RECORD
