Metadata-Version: 2.1
Name: sims
Version: 2.0.2
Summary: Python module to read Cameca (nano)SIMS data files. 
Home-page: https://github.com/zanpeeters/sims
Author: Zan Peeters
Author-email: me@example.com
License: BSD 3-Clause Clear
Keywords: sims nanosims mass-spectrometry Cameca file-format
Classifier: License :: OSI Approved :: BSD License
Classifier: Programming Language :: Python :: 3
Classifier: Development Status :: 4 - Beta
Classifier: Development Status :: 5 - Production/Stable
Classifier: Intended Audience :: Science/Research
Classifier: Topic :: Scientific/Engineering
Requires-Python: >=3.8
License-File: LICENSE.md
Requires-Dist: matplotlib
Requires-Dist: scikit-image (>=0.19)
Requires-Dist: scipy
Requires-Dist: xarray
